pywhat/Data/file_signatures.json
pywhat/Data/mac_vendors.json
pywhat/Data/mastercard_companies.json
pywhat/Data/phone_codes.json
pywhat/Data/regex.json
pywhat/__init__.py
pywhat/__main__.py
pywhat/filter.py
pywhat/helper.py
pywhat/identifier.py
pywhat/magic_numbers.py
pywhat/printer.py
pywhat/regex_identifier.py
pywhat/what.py
pywhat-5.1.0.dist-info/entry_points.txt
pywhat-5.1.0.dist-info/LICENSE
pywhat-5.1.0.dist-info/WHEEL
pywhat-5.1.0.dist-info/METADATA
pywhat-5.1.0.dist-info/RECORD
