Metadata-Version: 2.1
Name: pywhat
Version: 5.1.0
Summary: What is that thing?
License: MIT
Author: Bee
Author-email: github@skerritt.blog
Requires-Python: >=3.6,<4.0
Classifier: License :: OSI Approved :: MIT License
Classifier: Programming Language :: Python :: 3
Classifier: Programming Language :: Python :: 3.6
Classifier: Programming Language :: Python :: 3.7
Classifier: Programming Language :: Python :: 3.8
Classifier: Programming Language :: Python :: 3.9
Provides-Extra: optimize
Requires-Dist: click (>=7.1.2,<8.0.0)
Requires-Dist: orjson (>=3.6.1,<4.0.0); extra == "optimize"
Requires-Dist: rich (>=9.9,<11.0)
Project-URL: Documentation, https://github.com/bee-san/pyWhat/wiki
